{
  "parent": "minecraft:recipes/root",
  "criteria": {
    "has_blue_snowbelle": {
      "conditions": {
        "items": [
          {
            "items": [
              "regions_unexplored:blue_snowbelle"
            ]
          }
        ]
      },
      "trigger": "minecraft:inventory_changed"
    },
    "has_the_recipe": {
      "conditions": {
        "recipe": "regions_unexplored:blue_dye_from_blue_snowbelle"
      },
      "trigger": "minecraft:recipe_unlocked"
    }
  },
  "requirements": [
    [
      "has_blue_snowbelle",
      "has_the_recipe"
    ]
  ],
  "rewards": {
    "recipes": [
      "regions_unexplored:blue_dye_from_blue_snowbelle"
    ]
  }
}