{
  "type": "regions_unexplored:giant_cypress_tree",
  "config": {
    "branch_provider": {
      "type": "minecraft:simple_state_provider",
      "state": {
        "Name": "regions_unexplored:cypress_branch",
        "Properties": {
          "facing": "north"
        }
      }
    },
    "foliage_provider": {
      "type": "minecraft:simple_state_provider",
      "state": {
        "Name": "regions_unexplored:cypress_leaves",
        "Properties": {
          "distance": "7",
          "persistent": "false",
          "waterlogged": "false"
        }
      }
    },
    "minimum_size": 25,
    "size_variation": 5,
    "trunk_provider": {
      "type": "minecraft:simple_state_provider",
      "state": {
        "Name": "regions_unexplored:cypress_log",
        "Properties": {
          "axis": "y"
        }
      }
    }
  }
}